MANIFEST.in
README.md
setup.cfg
setup.py
nannotate/__init__.py
nannotate/__main__.py
nannotate/_commands.py
nannotate/annotate.py
nannotate/utils.py
nannotate.egg-info/PKG-INFO
nannotate.egg-info/SOURCES.txt
nannotate.egg-info/dependency_links.txt
nannotate.egg-info/not-zip-safe
nannotate.egg-info/top_level.txt
nannotate/comm/__init__.py
nannotate/comm/handler.py
nannotate/comm/io.py
nannotate/console/__init__.py
nannotate/console/io.py
nannotate/ws/__init__.py
nannotate/ws/handler.py
nannotate/ws/io.py